[  
    {  
       "_id":"1124939284039946240",
       "to":"nilemedia1",
       "from":"NileMedia1",
       "body":"Looking for something great to watch today?\n\nThe Nile Media App provides a catalogue of educational programmes, documentaries and movies at the most affordable data rates.\n\nFor unlimited access and viewing, download the app on your Android device now - https://t.co/hPUajCBWIL. https://t.co/UU5Dw9k4vq",
       "time":"2019-05-05T07:30:00.000Z"
    },
    {  
       "_id":"1123620706837782530",
       "to":"nilemedia1",
       "from":"NileMedia1",
       "body":"@TimModise @Davos",
       "time":"2019-05-01T16:10:27.000Z"
    },
    {  
       "_id":"1123620080053641216",
       "to":"nilemedia1",
       "from":"NileMedia1",
       "body":"The 4th Industrial Revolution is creating new categories of jobs and wholly displacing others.\n\nHow can policy-makers and business prepare workers and markets for both old and new occupations?\n\nWatch the @wef discussion on the Nile Media App at 20h41 https://t.co/hPUajCTy7l. https://t.co/gP8GlvU646",
       "time":"2019-05-01T16:07:57.000Z"
    },
    {  
       "_id":"1123562820451360768",
       "to":"nilemedia1",
       "from":"NileMedia1",
       "body":"Download The Nile Media App to watch the documentary at 15h00, with repeats at 19h00 and 23h00 - https://t.co/hPUajCTy7l. \n\n@_cosatu @SAFTU_media @TimModise @Zwelinzima1 @IrvinJimSA @Numsa_Media",
       "time":"2019-05-01T12:20:25.000Z"
    },
    {  
       "_id":"1123561898950254592",
       "to":"nilemedia1",
       "from":"NileMedia1",
       "body":"Is Workers' Day worth celebrating with SA's high unemployment rate?\n\nThe public was asked whether it feels enough is being done to address the unemployment crisis, challenge worker issues and champion the class struggle.\n\nWatch the doccie on the Nile Media App at 15h00. #MayDay https://t.co/M7Qu0pzeVD",
       "time":"2019-05-01T12:16:46.000Z"
    },
    {  
       "_id":"1123559780663083008",
       "to":"nilemedia1",
       "from":"NileMedia1",
       "body":"Download The Nile Media App to watch the documentary at 15h00 -  https://t.co/hPUajCTy7l.\n\n@_cosatu @SAFTU_media @TimModise @Zwelinzima1 @IrvinJimSA @Numsa_Media",
       "time":"2019-05-01T12:08:21.000Z"
    },
    {  
       "_id":"1123559242315829248",
       "to":"nilemedia1",
       "from":"NileMedia1",
       "body":"@_cosatu @SAFTU_media @TimModise @Zwelinzima1 @IrvinJimSA @Numsa_Media",
       "time":"2019-05-01T12:06:12.000Z"
    },
    {  
       "_id":"1123558222068166657",
       "to":"nilemedia1",
       "from":"NileMedia1",
       "body":"Is Workers' Day worth celebrating with SA's high unemployment rate?\n\nThe public was asked whether they feel enough is being done to address the unemployment crisis, challenge worker issues and champion the class struggle.\n\nWatch the doccie on the Nile Media App at 15h00. #MayDay https://t.co/MACEcxdM8N",
       "time":"2019-05-01T12:02:09.000Z"
    },
    {  
       "_id":"1123552445278375936",
       "to":"nilemedia1",
       "from":"NileMedia1",
       "body":"As part of the Workers' Day celebrations and commemoration, Nile Media will be airing documentaries that explore the history and significance of the public holiday; as well as the current state of the Workers' Struggle.\n\nDownload to watch - https://t.co/hPUajCTy7l. #WorkersDay https://t.co/6Rzvh6O7sc",
       "time":"2019-05-01T11:39:12.000Z"
    }
]